fluidly_sqlalchemy-0.1.1-py3.7-nspkg.pth
fluidly/sqlalchemy/__init__.py
fluidly/sqlalchemy/db.py
fluidly/sqlalchemy/materialised_view_mixin.py
fluidly/sqlalchemy/py.typed
fluidly/sqlalchemy/timestamp_mixin.py
fluidly/sqlalchemy/upsert.py
fluidly/sqlalchemy/user_action_mixin.py
fluidly_sqlalchemy-0.1.1.dist-info/METADATA
fluidly_sqlalchemy-0.1.1.dist-info/WHEEL
fluidly_sqlalchemy-0.1.1.dist-info/namespace_packages.txt
fluidly_sqlalchemy-0.1.1.dist-info/top_level.txt
fluidly_sqlalchemy-0.1.1.dist-info/RECORD
